torchmimic/__init__.py
torchmimic/metrics.py
torchmimic/utils.py
torchmimic/benchmarks/__init__.py
torchmimic/benchmarks/decompensation/__init__.py
torchmimic/benchmarks/decompensation/decompensation_benchmark.py
torchmimic/benchmarks/ihm/__init__.py
torchmimic/benchmarks/ihm/ihm_benchmark.py
torchmimic/benchmarks/los/__init__.py
torchmimic/benchmarks/los/los_benchmark.py
torchmimic/benchmarks/phenotyping/__init__.py
torchmimic/benchmarks/phenotyping/phenotyping_benchmark.py
torchmimic/data/__init__.py
torchmimic/data/base_dataset.py
torchmimic/data/preprocessing.py
torchmimic/data/readers.py
torchmimic/data/utils.py
torchmimic/data/decompensation/__init__.py
torchmimic/data/decompensation/dataset.py
torchmimic/data/discretizers/discretizer_config.json
torchmimic/data/ihm/__init__.py
torchmimic/data/ihm/dataset.py
torchmimic/data/los/__init__.py
torchmimic/data/los/dataset.py
torchmimic/data/multitask/__init__.py
torchmimic/data/multitask/batch_gen.py
torchmimic/data/multitask/train_multitask.py
torchmimic/data/multitask/utils.py
torchmimic/data/normalizers/decomp_ts0.8.input_str:previous.n1e5.start_time:zero.normalizer
torchmimic/data/normalizers/decomp_ts1.0.input_str:previous.n1e5.start_time:zero.normalizer
torchmimic/data/normalizers/ihm_ts0.8.input_str:previous.start_time:zero.normalizer
torchmimic/data/normalizers/ihm_ts1.0.input_str:previous.start_time:zero.normalizer
torchmimic/data/normalizers/ihm_ts2.0.input_str:previous.start_time:zero.normalizer
torchmimic/data/normalizers/los_ts0.8.input_str:previous.start_time:zero.n5e4.normalizer
torchmimic/data/normalizers/los_ts1.0.input_str:previous.start_time:zero.n5e4.normalizer
torchmimic/data/normalizers/mult_ts1.0.input_str:previous.start_time:zero.normalizer
torchmimic/data/normalizers/ph_ts1.0.input_str:previous.start_time:zero.normalizer
torchmimic/data/phenotyping/__init__.py
torchmimic/data/phenotyping/dataset.py
torchmimic/loggers/__init__.py
torchmimic/loggers/base_logger.py
torchmimic-0.0.6.dist-info/LICENSE.md
torchmimic-0.0.6.dist-info/METADATA
torchmimic-0.0.6.dist-info/WHEEL
torchmimic-0.0.6.dist-info/top_level.txt
torchmimic-0.0.6.dist-info/RECORD
