Metadata-Version: 2.1
Name: torchmimic
Version: 0.0.6
Summary: MIMIC Benchmark in PyTorch.
Home-page: https://github.com/kingrc15/torchmimic
Author: Ryan King
Author-email: kingrc15@tamu.edu
License: MIT
Platform: UNKNOWN
Classifier: Programming Language :: Python :: 3
Classifier: License :: OSI Approved :: MIT License
Requires-Python: ~=3.6
License-File: LICENSE.md
Requires-Dist: torch
Requires-Dist: scikit-learn
Requires-Dist: numpy
Requires-Dist: wandb
Provides-Extra: local
Requires-Dist: pytest ; extra == 'local'
Requires-Dist: black ; extra == 'local'
Requires-Dist: setuptools ; extra == 'local'
Requires-Dist: sphinx ; extra == 'local'
